lflatten/__init__.py
lflatten/_flatten.py
lflatten/_flatten.pyi
lflatten/_types.py
lflatten/_unflatten.py
lflatten/_unflatten.pyi
lflatten-0.1.0.dist-info/licenses/LICENSE
lflatten-0.1.0.dist-info/METADATA
lflatten-0.1.0.dist-info/WHEEL
lflatten-0.1.0.dist-info/top_level.txt
lflatten-0.1.0.dist-info/RECORD
