Metadata-Version: 2.4
Name: lflatten
Version: 0.1.0
Summary: Literal flatten(or unflatten) for data structures
Author-email: Daniel <danielmenezes0822@gmail.com>
License: MIT License
Project-URL: Homepage, https://github.com/oDaniel728/lflatten
Project-URL: Repository, https://github.com/oDaniel728/lflatten
Keywords: python,lib,flatten,lflatten,unflatten,compress
Classifier: Programming Language :: Python :: 3
Classifier: License :: OSI Approved :: MIT License
Requires-Python: >=3.11
License-File: LICENSE
Dynamic: license-file
